{"version": "1", "message": "ERROR: Hidden Testcases server unreachable.", "problem_id": "ads1_m12_a1", "user_id": "bhaskaravsravya", "score": {"sample": {"0": {"execution_time": 0.2855379581451416, "passed": true}, "1": {"execution_time": 0.450838565826416, "passed": true}, "2": {"execution_time": 0.31650209426879883, "passed": true}, "3": {"execution_time": 0.5148804187774658, "passed": true}, "4": {"execution_time": 0.3933289051055908, "passed": true}, "5": {"execution_time": 0.5203068256378174, "passed": false}}}, "check_style_score": "0/1"}